lambda_generator/__init__.py
lambda_generator/cli.py
lambda_generator/functions.py
lambda_generator/templates/python_serverless_docker_jenkins/.flake8
lambda_generator/templates/python_serverless_docker_jenkins/Jenkinsfile
lambda_generator/templates/python_serverless_docker_jenkins/Makefile
lambda_generator/templates/python_serverless_docker_jenkins/__init__.py
lambda_generator/templates/python_serverless_docker_jenkins/dockers/Dockerfile-deploy
lambda_generator/templates/python_serverless_docker_jenkins/dockers/Dockerfile-lint
lambda_generator/templates/python_serverless_docker_jenkins/dockers/Dockerfile-test
lambda_generator/templates/python_serverless_docker_jenkins/main.py
lambda_generator/templates/python_serverless_docker_jenkins/package-lock.json
lambda_generator/templates/python_serverless_docker_jenkins/package.json
lambda_generator/templates/python_serverless_docker_jenkins/requirements-dev.txt
lambda_generator/templates/python_serverless_docker_jenkins/requirements.txt
lambda_generator/templates/python_serverless_docker_jenkins/serverless.yml
lambda_generator/templates/python_serverless_docker_jenkins/tests/__init__.py
lambda_generator/templates/python_serverless_docker_jenkins/tests/test_main.py
lambda_generator-0.1.0.dist-info/entry_points.txt
lambda_generator-0.1.0.dist-info/WHEEL
lambda_generator-0.1.0.dist-info/METADATA
lambda_generator-0.1.0.dist-info/RECORD
